flashcam/__init__.py
flashcam/base_camera2.py
flashcam/config.py
flashcam/daq_server.py
flashcam/direct.py
flashcam/izmq_receiver.py
flashcam/mmapwr.py
flashcam/real_camera.py
flashcam/stream_enhancer.py
flashcam/text_write.py
flashcam/uniwrec.py
flashcam/uniwrec_io.py
flashcam/uniwrec_keys.py
flashcam/uniwrec_manip.py
flashcam/usbcheck.py
flashcam/v4lc.py
flashcam/version.py
flashcam/web.py
flashcam/data/BEAM_OFF.jpg
flashcam/data/BEAM_ON_.jpg
flashcam/data/CONTFO__.ttf
flashcam/data/CONTFU__.ttf
flashcam/data/CONTF___.ttf
flashcam/data/DET_NRDY.jpg
flashcam/data/DET_RDY_.jpg
flashcam/data/OpenSans-Bold.ttf
flashcam/data/OpenSans-BoldItalic.ttf
flashcam/data/OpenSans-ExtraBold.ttf
flashcam/data/OpenSans-ExtraBoldItalic.ttf
flashcam/data/OpenSans-Italic.ttf
flashcam/data/OpenSans-Light.ttf
flashcam/data/OpenSans-LightItalic.ttf
flashcam/data/OpenSans-Regular.ttf
flashcam/data/OpenSans-Semibold.ttf
flashcam/data/OpenSans-SemiboldItalic.ttf
flashcam/data/PixelFJVerdana12pt.ttf
flashcam/data/TypographerFraktur-Bold.ttf
flashcam/data/TypographerFraktur-Contour.ttf
flashcam/data/TypographerFraktur-Medium.ttf
flashcam/data/TypographerFraktur-Shadow.ttf
flashcam/data/Uni_Sans_Heavy.otf
flashcam/data/Uni_Sans_Heavy_Italic.otf
flashcam/data/Uni_Sans_Thin.otf
flashcam/data/Uni_Sans_Thin_Italic.otf
flashcam/data/VT323-Regular.ttf
flashcam/data/coders_crux.ttf
flashcam/data/digital-7.mono.ttf
flashcam/data/digital-7.regular.ttf
flashcam/data/good_times_rg.otf
flashcam/data/hemi_head_bd_it.otf
flashcam/data/monoskop.jpg
flashcam/data/pattern_acircles.png
flashcam/data/pattern_chessboard.png
flashcam/data/pixelFJ8pt1__.TTF
flashcam/data/prstart.ttf
flashcam/data/prstartk.ttf
flashcam/data/px10.ttf
flashcam/data/retganon.ttf
flashcam/data/small_pixel.ttf
flashcam/data/square_pixel-7.ttf
flashcam/data/ubu_2204.jpg
flashcam/data/visitor1.ttf
flashcam/data/visitor2.ttf
flashcam/data/win_rain.jpg
flashcam/data/win_skull.jpg
flashcam/data/win_storm.jpg
flashcam/data/win_winter.jpg
flashcam-1.13.4.dist-info/METADATA
flashcam-1.13.4.dist-info/WHEEL
flashcam-1.13.4.dist-info/top_level.txt
flashcam-1.13.4.dist-info/RECORD
