Metadata-Version: 2.4
Name: flashcam
Version: 1.13.4
Summary: Composition of scripts to control a web camera
Home-page: https://gitlab.com/jaromrax/flashcam
Author: jaromrax
Author-email: jaromrax@gmail.com
License: GPL2
Requires-Dist: opencv-python
Requires-Dist: fire
Requires-Dist: v4l2py
Requires-Dist: flask_httpauth
Requires-Dist: gunicorn
Requires-Dist: numpy
Requires-Dist: imutils
Requires-Dist: pandas
Requires-Dist: matplotlib
Requires-Dist: psutil
Requires-Dist: pyserial-asyncio
Requires-Dist: imagezmq
Requires-Dist: notifator
Requires-Dist: pyautogui
Requires-Dist: importlib_resources
Requires-Dist: requests
Requires-Dist: pynput
Requires-Dist: console
Requires-Dist: pillow
Requires-Dist: scikit-video
Requires-Dist: tdb_io
Requires-Dist: paho-mqtt
Requires-Dist: screeninfo
Dynamic: author
Dynamic: author-email
Dynamic: description
Dynamic: description-content-type
Dynamic: home-page
Dynamic: license
Dynamic: requires-dist
Dynamic: summary
